Practica_2/mux2_4.v
module mux2_4(output wire [3:0] Out, input wire [3:0] A, input wire [3:0] B, input wire s);
  
  assign Out = (s) ? B : A;
  
endmodule

Practica_2/mux4_1.v
module mux4_1(output reg out, input wire a, b, c, d, input wire [1:0] S);

  always @(a,b,c,d,S) begin
    case (S)
      2'b00: out = a;
      2'b01: out = b;
      2'b10: out = c;
      2'b11: out = d;
    endcase  
  end

endmodule

Practica_2/cl.v
module cl(output wire out, input wire a, input wire b, input wire [1:0] S);

  wire xor_out, not_out, and_out, or_out;  // SE DECLARAN LOS CABLES DE SALIDA DE LAS PUESTAS LÓGICAS
  
  and and_door(and_out, a, b);  // SE DECLARA UNA PUERTA AND A LA QUE LE ENTRAN A Y B Y SALE AND_DOOR
  or or_door(or_out, a, b);  // SE DECLARA UNA PUERTA OR A LA QUE LE ENTRAN A Y B Y SALE OR_DOOR
  xor xor_door(xor_out, a, b);  // SE DECLARA UNA PUERTA XOR A LA QUE LE ENTRA A Y B Y SALE EL CABLE XOR_OUT
  not not_door(not_out, a);  // SE DECLARA UNA PUERTA NOT A LA QUE LE ENTRAN A Y SALE NOT_DOOR
  // mux4_1 mux_cl(out, xor_out, and_out, or_out, not_out, S);  // DECLARAMOS UN MUX4_1 AL QUE LE ENTRA COMO PARAMETROS LAS SALIDAS DE LAS PUERTAS LÓGICAS ANTERIORES, UNA SEÑAL DE SELECCIÓN S Y DA COMO SALIDA LA SEÑAL OUT DE LA CELDA LOGICA
  mux4_1 mux_cl(out, and_out, or_out, xor_out, not_out, S);  // DECLARAMOS UN MUX4_1 AL QUE LE ENTRA COMO PARAMETROS LAS SALIDAS DE LAS PUERTAS LÓGICAS ANTERIORES, UNA SEÑAL DE SELECCIÓN S Y DA COMO SALIDA LA SEÑAL OUT DE LA CELDA LOGICA
                                                              
endmodule

Practica_2/ul4.v
module ul4(output wire[3:0] Out, input wire[3:0] A, input wire[3:0] B, input wire [1:0] S);

  cl cl_0(Out(0), A(0), B(0), S);
  cl cl_1(Out(1), A(1), B(1), S);
  cl cl_2(Out(3), A(2), B(2), S);
  cl cl_3(Out(4), A(4), B(4), S);

endmodule



// NO ENTIENDO COMO SE IMPLEMENTA LA UNIDAD LOGICA

Practica_2/fa.v
module fa(output wire c_out, sum, input wire a, b, c_in);
  
  fa fa1





endmodule

Practica_2/sum4.v
module sum4(output wire[3:0] S, output wire c_out, input wire[3:0] A, input wire[3:0] B, input wire c_in);
  
  wire carry1, carry2, carry3;
  
  fa fa_0(carry1, S[0], A[0], B[0], c_in);
  fa fa_1(carry2, S[1], A[1], B[1], carry1);
  fa fa_2(carry3, S[2], A[2], B[2], carry2);
  fa fa_3(c_out, S[3], A[3], B[3], carry3);

endmodule

Practica_2/compl1.v
module compl1(output wire [3:0] Out, input wire [3:0] Inp, input wire cpl);

  assign Out = cpl ? ~Inp : Inp;
  
  // mux2_4 (Out, Inp, ~Inp, cpl); Otra posible forma de implementación

endmodule

Practica_2/alu.v
module alu(output wire [3:0] R, output wire zero, carry, sign, input wire [3:0] A, B, input wire [1:0] ALUOp, input wire l);

  wire op1_A, op2_B, cpl, cin0;
  wire [3:0] OP1, OP2, mux2_out, sum4_out, ul4_out;

  mux2_4 mux2_4_1 (OP1, 4'b0000, A, op1_A);
  mux2_4 mux2_4_2 (mux2_out, A, B, op2_B);
  compl1 compl1_1 (OP2, mux2_out, cpl);
  sum4 sum4_1 (sum4_out, carry, OP1, OP2, cin0);
  ul4 ul4_1 (ul4_out, OP1, OP2, ALUOp);
  mux2_4 mux2_4_3 (R, sum4_out, ul4_out, l);

  assign zero = ~(R[0]|R[1]|R[2]|R[3]);
  assign sign = R[3];

  assign op1_A = l | ALUOp[1];
  assign op2_B = l | ALUOp[1] | ALUOp[0];
  assign cpl = ((~l) & (~ALUOp[1])) | ((~l) & ALUOp[0]);
  assign cin0 = (~ALUOp[1]) | ALUOp[0];

endmodule

// EJECUCION
// $ iverilog -o ripple ripple_carry_adder.v ripple_carry_adder_tb.v
// $ vvp ripple

Practica_2/alu_tb.v
// Testbench para modulo alu
`timescale 1 ns / 10 ps //Directiva que fija la unidad de tiempo de simulación y la precision de la unidad
module alu_tb;
//declaracion de señales
reg [1:0] t_Op;
reg t_l;
reg [3:0] t_A, t_B;
wire [3:0] t_R;
wire t_z, t_c, t_s;
integer errores;
//instancia del modulo a testear
alu mat(t_R, t_z, t_c, t_s, t_A, t_B, t_Op, t_l);
initial
begin
  $dumpfile("alu.vcd");
  $dumpvars;
  $monitor("tiempo=%0d A=%b B=%b L=%b Op=%b R=%b, Z=%b, C=%b, S=%b", $time, t_A, t_B, t_l, t_Op, t_R, t_z, t_c, t_s);

  errores = 0;
  t_l = 1'b0;
  repeat(2)
	begin
	t_Op = 2'b0;
	repeat(4)
		begin
		  t_A = 4'b0;
		  repeat(16) 
		  begin
			t_B = 4'b0;
			repeat(16) 
			begin
				# 2 check;
				t_B = t_B + 1;
			end
			t_A = t_A + 1;
		  end
		  t_Op = t_Op + 1;
		end
		t_l = t_l + 1;
	end
	$display("Encontradas %d operaciones erroneas", errores);
  //fin simulacion
  $finish;
end

// Tarea para hacer la comprobación automática de resultados
task check;
reg [4:0] result;
reg flag_zero, flag_carry, flag_sign;
begin
	// Si las operaciones son lógicas
	if (t_l)
	begin
		case (t_Op)
			2'b00: result[3:0] = t_A & t_B;
			2'b01: result[3:0] = t_A | t_B;
			2'b10: result[3:0] = t_A ^ t_B;
			2'b11: result[3:0] = ~t_A;
			default: $display("ERROR. Valor no esperado para t_Op: %b", t_Op);
		endcase
		flag_carry = 1'bx;
		flag_sign = 1'bx;
	end
	else
	begin
		case (t_Op)
			2'b00: result = (t_A ^4'b1111) + 4'b0001;
			2'b01: result = (t_B ^4'b1111) + 4'b0001;
			2'b10: result = t_A + t_B;
			2'b11: result = t_A + ((t_B ^4'b1111) + 1);
			default: $display("ERROR. Valor no esperado para t_Op: %b", t_Op);
		endcase
		flag_carry = result[4];
		flag_sign = result[3];
		if (flag_sign !== t_s || flag_carry !== t_c)
		begin
			errores = errores + 1;
			$display("ERROR con operacion L=%b, OP=%b A=%b B=%b", t_l, t_Op, t_A, t_B);
			if (flag_sign !== t_s)
				$display("ERROR. Flag de signo esperado %b, obtenido %b", flag_sign, t_s);
			if (flag_carry !== t_c)
				$display("\tFlag de acarreo esperado %b, obtenido %b", flag_carry, t_c);
		end
	end

	flag_zero = ~| result[3:0];
	if (result[3:0] !== t_R || flag_zero !== t_z)
	begin
		errores = errores + 1;
		$display("ERROR con operacion L=%b, OP=%b A=%b B=%b", t_l, t_Op, t_A, t_B);
		if (result[3:0] !== t_R)
			$display("\tResultado esperado %b, obtenido %b", result[3:0], t_R);
		if (flag_zero !== t_z)
			$display("\tFlag de cero esperado %b, obtenido %b", flag_zero, t_z);
	end
end
endtask
endmodule

Practica_2/alu.vcd
$date
	Tue Nov  8 16:05:20 2022
$end
$version
	Icarus Verilog
$end
$timescale
	10ps
$end
$scope module alu_tb $end
$var wire 1 ! t_z $end
$var wire 1 " t_s $end
$var wire 1 # t_c $end
$var wire 4 $ t_R [3:0] $end
$var reg 4 % t_A [3:0] $end
$var reg 4 & t_B [3:0] $end
$var reg 2 ' t_Op [1:0] $end
$var reg 1 ( t_l $end
$var integer 32 ) errores [31:0] $end
$scope module mat $end
$var wire 4 * A [3:0] $end
$var wire 2 + ALUOp [1:0] $end
$var wire 4 , B [3:0] $end
$var wire 1 - cin0 $end
$var wire 1 . cpl $end
$var wire 1 ( l $end
$var wire 1 / op1_A $end
$var wire 1 0 op2_B $end
$var wire 1 ! zero $end
$var wire 4 1 ul4_out [3:0] $end
$var wire 4 2 sum4_out [3:0] $end
$var wire 1 " sign $end
$var wire 4 3 mux2_out [3:0] $end
$var wire 1 # carry $end
$var wire 4 4 R [3:0] $end
$var wire 4 5 OP2 [3:0] $end
$var wire 4 6 OP1 [3:0] $end
$scope module compl1_1 $end
$var wire 1 . cpl $end
$var wire 4 7 Out [3:0] $end
$var wire 4 8 Inp [3:0] $end
$upscope $end
$scope module mux2_4_1 $end
$var wire 4 9 A [3:0] $end
$var wire 4 : B [3:0] $end
$var wire 1 / s $end
$var wire 4 ; Out [3:0] $end
$upscope $end
$scope module mux2_4_2 $end
$var wire 4 < A [3:0] $end
$var wire 4 = B [3:0] $end
$var wire 1 0 s $end
$var wire 4 > Out [3:0] $end
$upscope $end
$scope module mux2_4_3 $end
$var wire 1 ( s $end
$var wire 4 ? Out [3:0] $end
$var wire 4 @ B [3:0] $end
$var wire 4 A A [3:0] $end
$upscope $end
$scope module sum4_1 $end
$var wire 4 B A [3:0] $end
$var wire 4 C B [3:0] $end
$var wire 1 - c_in $end
$var wire 1 D carry3 $end
$var wire 1 E carry2 $end
$var wire 1 F carry1 $end
$var wire 1 # c_out $end
$var wire 4 G S [3:0] $end
$scope module fa_0 $end
$var wire 1 H a $end
$var wire 1 I b $end
$var wire 1 - c_in $end
$var wire 1 J sum $end
$var wire 1 F c_out $end
$upscope $end
$scope module fa_1 $end
$var wire 1 K a $end
$var wire 1 L b $end
$var wire 1 F c_in $end
$var wire 1 M sum $end
$var wire 1 E c_out $end
$upscope $end
$scope module fa_2 $end
$var wire 1 N a $end
$var wire 1 O b $end
$var wire 1 E c_in $end
$var wire 1 P sum $end
$var wire 1 D c_out $end
$upscope $end
$scope module fa_3 $end
$var wire 1 Q a $end
$var wire 1 R b $end
$var wire 1 D c_in $end
$var wire 1 S sum $end
$var wire 1 # c_out $end
$upscope $end
$upscope $end
$scope module ul4_1 $end
$var wire 4 T A [3:0] $end
$var wire 4 U B [3:0] $end
$var wire 2 V S [1:0] $end
$var wire 4 W Out [3:0] $end
$scope module cl_0 $end
$var wire 2 X S [1:0] $end
$var wire 1 Y a $end
$var wire 1 Z and_out $end
$var wire 1 [ b $end
$var wire 1 \ not_out $end
$var wire 1 ] or_out $end
$var wire 1 ^ xor_out $end
$var wire 1 _ out $end
$scope module mux_cl $end
$var wire 2 ` S [1:0] $end
$var wire 1 Z a $end
$var wire 1 ] b $end
$var wire 1 ^ c $end
$var wire 1 \ d $end
$var reg 1 _ out $end
$upscope $end
$upscope $end
$scope module cl_1 $end
$var wire 2 a S [1:0] $end
$var wire 1 b a $end
$var wire 1 c and_out $end
$var wire 1 d b $end
$var wire 1 e not_out $end
$var wire 1 f or_out $end
$var wire 1 g xor_out $end
$var wire 1 h out $end
$scope module mux_cl $end
$var wire 2 i S [1:0] $end
$var wire 1 c a $end
$var wire 1 f b $end
$var wire 1 g c $end
$var wire 1 e d $end
$var reg 1 h out $end
$upscope $end
$upscope $end
$scope module cl_2 $end
$var wire 2 j S [1:0] $end
$var wire 1 k a $end
$var wire 1 l and_out $end
$var wire 1 m b $end
$var wire 1 n not_out $end
$var wire 1 o or_out $end
$var wire 1 p xor_out $end
$var wire 1 q out $end
$scope module mux_cl $end
$var wire 2 r S [1:0] $end
$var wire 1 l a $end
$var wire 1 o b $end
$var wire 1 p c $end
$var wire 1 n d $end
$var reg 1 q out $end
$upscope $end
$upscope $end
$scope module cl_3 $end
$var wire 2 s S [1:0] $end
$var wire 1 t a $end
$var wire 1 u and_out $end
$var wire 1 v b $end
$var wire 1 w not_out $end
$var wire 1 x or_out $end
$var wire 1 y xor_out $end
$var wire 1 z out $end
$scope module mux_cl $end
$var wire 2 { S [1:0] $end
$var wire 1 u a $end
$var wire 1 x b $end
$var wire 1 y c $end
$var wire 1 w d $end
$var reg 1 z out $end
$upscope $end
$upscope $end
$upscope $end
$upscope $end
$scope task check $end
$var reg 1 | flag_carry $end
$var reg 1 } flag_sign $end
$var reg 1 ~ flag_zero $end
$var reg 5 !" result [4:0] $end
$upscope $end
$upscope $end
$enddefinitions $end
#0
$dumpvars
bx !"
x~
x}
x|
b0 {
0z
1y
1x
1w
1v
0u
0t
b0 s
b0 r
0q
1p
1o
1n
1m
0l
0k
b0 j
b0 i
0h
1g
1f
1e
1d
0c
0b
b0 a
b0 `
0_
1^
1]
1\
1[
0Z
0Y
b0 X
b0 W
b0 V
b1111 U
b0 T
0S
1R
0Q
0P
1O
0N
0M
1L
0K
0J
1I
0H
b0 G
1F
1E
1D
b1111 C
b0 B
b0 A
b0 @
b0 ?
b0 >
b0 =
b0 <
b0 ;
b0 :
b0 9
b0 8
b1111 7
b0 6
b1111 5
b0 4
b0 3
b0 2
b0 1
00
0/
1.
1-
b0 ,
b0 +
b0 *
b0 )
0(
b0 '
b0 &
b0 %
b0 $
1#
0"
1!
$end
#200
b1 &
b1 ,
b1 =
1~
0}
1|
b10000 !"
#400
b10 &
b10 ,
b10 =
#600
b11 &
b11 ,
b11 =
#800
b100 &
b100 ,
b100 =
#1000
b101 &
b101 ,
b101 =
#1200
b110 &
b110 ,
b110 =
#1400
b111 &
b111 ,
b111 =
#1600
b1000 &
b1000 ,
b1000 =
#1800
b1001 &
b1001 ,
b1001 =
#2000
b1010 &
b1010 ,
b1010 =
#2200
b1011 &
b1011 ,
b1011 =
#2400
b1100 &
b1100 ,
b1100 =
#2600
b1101 &
b1101 ,
b1101 =
#2800
b1110 &
b1110 ,
b1110 =
#3000
b1111 &
b1111 ,
b1111 =
#3200
0!
1"
1S
0#
1P
0D
b1111 $
b1111 4
b1111 ?
1M
0E
b1111 2
b1111 A
b1111 G
1J
0F
0]
0^
0I
0[
b1110 5
b1110 7
b1110 C
b1110 U
b1 3
b1 8
b1 >
b1 %
b1 *
b1 :
b1 <
b0 &
b0 ,
b0 =
#3400
b1 &
b1 ,
b1 =
0~
1}
0|
b1111 !"
#3600
b10 &
b10 ,
b10 =
#3800
b11 &
b11 ,
b11 =
#4000
b100 &
b100 ,
b100 =
#4200
b101 &
b101 ,
b101 =
#4400
b110 &
b110 ,
b110 =
#4600
b111 &
b111 ,
b111 =
#4800
b1000 &
b1000 ,
b1000 =
#5000
b1001 &
b1001 ,
b1001 =
#5200
b1010 &
b1010 ,
b1010 =
#5400
b1011 &
b1011 ,
b1011 =
#5600
b1100 &
b1100 ,
b1100 =
#5800
b1101 &
b1101 ,
b1101 =
#6000
b1110 &
b1110 ,
b1110 =
#6200
b1111 &
b1111 ,
b1111 =
#6400
b1110 $
b1110 4
b1110 ?
0J
1F
b1110 2
b1110 A
b1110 G
1M
1]
1^
0f
0g
1I
0L
1[
0d
b1101 5
b1101 7
b1101 C
b1101 U
b10 3
b10 8
b10 >
b10 %
b10 *
b10 :
b10 <
b0 &
b0 ,
b0 =
#6600
b1 &
b1 ,
b1 =
b1110 !"
#6800
b10 &
b10 ,
b10 =
#7000
b11 &
b11 ,
b11 =
#7200
b100 &
b100 ,
b100 =
#7400
b101 &
b101 ,
b101 =
#7600
b110 &
b110 ,
b110 =
#7800
b111 &
b111 ,
b111 =
#8000
b1000 &
b1000 ,
b1000 =
#8200
b1001 &
b1001 ,
b1001 =
#8400
b1010 &
b1010 ,
b1010 =
#8600
b1011 &
b1011 ,
b1011 =
#8800
b1100 &
b1100 ,
b1100 =
#9000
b1101 &
b1101 ,
b1101 =
#9200
b1110 &
b1110 ,
b1110 =
#9400
b1111 &
b1111 ,
b1111 =
#9600
b1101 $
b1101 4
b1101 ?
0M
b1101 2
b1101 A
b1101 G
1J
0F
0]
0^
0I
0[
b1100 5
b1100 7
b1100 C
b1100 U
b11 3
b11 8
b11 >
b11 %
b11 *
b11 :
b11 <
b0 &
b0 ,
b0 =
#9800
b1 &
b1 ,
b1 =
b1101 !"
#10000
b10 &
b10 ,
b10 =
#10200
b11 &
b11 ,
b11 =
#10400
b100 &
b100 ,
b100 =
#10600
b101 &
b101 ,
b101 =
#10800
b110 &
b110 ,
b110 =
#11000
b111 &
b111 ,
b111 =
#11200
b1000 &
b1000 ,
b1000 =
#11400
b1001 &
b1001 ,
b1001 =
#11600
b1010 &
b1010 ,
b1010 =
#11800
b1011 &
b1011 ,
b1011 =
#12000
b1100 &
b1100 ,
b1100 =
#12200
b1101 &
b1101 ,
b1101 =
#12400
b1110 &
b1110 ,
b1110 =
#12600
b1111 &
b1111 ,
b1111 =
#12800
1E
b1100 $
b1100 4
b1100 ?
0J
1F
0M
b1100 2
b1100 A
b1100 G
1P
1]
1^
1f
1g
0o
0p
1I
1L
0O
1[
1d
0m
b1011 5
b1011 7
b1011 C
b1011 U
b100 3
b100 8
b100 >
b100 %
b100 *
b100 :
b100 <
b0 &
b0 ,
b0 =
#13000
b1 &
b1 ,
b1 =
b1100 !"
#13200
b10 &
b10 ,
b10 =
#13400
b11 &
b11 ,
b11 =
#13600
b100 &
b100 ,
b100 =
#13800
b101 &
b101 ,
b101 =
#14000
b110 &
b110 ,
b110 =
#14200
b111 &
b111 ,
b111 =
#14400
b1000 &
b1000 ,
b1000 =
#14600
b1001 &
b1001 ,
b1001 =
#14800
b1010 &
b1010 ,
b1010 =
#15000
b1011 &
b1011 ,
b1011 =
#15200
b1100 &
b1100 ,
b1100 =
#15400
b1101 &
b1101 ,
b1101 =
#15600
b1110 &
b1110 ,
b1110 =
#15800
b1111 &
b1111 ,
b1111 =
#16000
0P
b1011 $
b1011 4
b1011 ?
1M
0E
b1011 2
b1011 A
b1011 G
1J
0F
0]
0^
0I
0[
b1010 5
b1010 7
b1010 C
b1010 U
b101 3
b101 8
b101 >
b101 %
b101 *
b101 :
b101 <
b0 &
b0 ,
b0 =
#16200
b1 &
b1 ,
b1 =
b1011 !"
#16400
b10 &
b10 ,
b10 =
#16600
b11 &
b11 ,
b11 =
#16800
b100 &
b100 ,
b100 =
#17000
b101 &
b101 ,
b101 =
#17200
b110 &
b110 ,
b110 =
#17400
b111 &
b111 ,
b111 =
#17600
b1000 &
b1000 ,
b1000 =
#17800
b1001 &
b1001 ,
b1001 =
#18000
b1010 &
b1010 ,
b1010 =
#18200
b1011 &
b1011 ,
b1011 =
#18400
b1100 &
b1100 ,
b1100 =
#18600
b1101 &
b1101 ,
b1101 =
#18800
b1110 &
b1110 ,
b1110 =
#19000
b1111 &
b1111 ,
b1111 =
#19200
b1010 $
b1010 4
b1010 ?
0J
1F
b1010 2
b1010 A
b1010 G
1M
1]
1^
0f
0g
1I
0L
1[
0d
b1001 5
b1001 7
b1001 C
b1001 U
b110 3
b110 8
b110 >
b110 %
b110 *
b110 :
b110 <
b0 &
b0 ,
b0 =
#19400
b1 &
b1 ,
b1 =
b1010 !"
#19600
b10 &
b10 ,
b10 =
#19800
b11 &
b11 ,
b11 =
#20000
b100 &
b100 ,
b100 =
#20200
b101 &
b101 ,
b101 =
#20400
b110 &
b110 ,
b110 =
#20600
b111 &
b111 ,
b111 =
#20800
b1000 &
b1000 ,
b1000 =
#21000
b1001 &
b1001 ,
b1001 =
#21200
b1010 &
b1010 ,
b1010 =
#21400
b1011 &
b1011 ,
b1011 =
#21600
b1100 &
b1100 ,
b1100 =
#21800
b1101 &
b1101 ,
b1101 =
#22000
b1110 &
b1110 ,
b1110 =
#22200
b1111 &
b1111 ,
b1111 =
#22400
b1001 $
b1001 4
b1001 ?
0M
b1001 2
b1001 A
b1001 G
1J
0F
0]
0^
0I
0[
b1000 5
b1000 7
b1000 C
b1000 U
b111 3
b111 8
b111 >
b111 %
b111 *
b111 :
b111 <
b0 &
b0 ,
b0 =
#22600
b1 &
b1 ,
b1 =
b1001 !"
#22800
b10 &
b10 ,
b10 =
#23000
b11 &
b11 ,
b11 =
#23200
b100 &
b100 ,
b100 =
#23400
b101 &
b101 ,
b101 =
#23600
b110 &
b110 ,
b110 =
#23800
b111 &
b111 ,
b111 =
#24000
b1000 &
b1000 ,
b1000 =
#24200
b1001 &
b1001 ,
b1001 =
#24400
b1010 &
b1010 ,
b1010 =
#24600
b1011 &
b1011 ,
b1011 =
#24800
b1100 &
b1100 ,
b1100 =
#25000
b1101 &
b1101 ,
b1101 =
#25200
b1110 &
b1110 ,
b1110 =
#25400
b1111 &
b1111 ,
b1111 =
#25600
1D
1"
1E
b1000 $
b1000 4
b1000 ?
0J
1F
0M
0P
b1000 2
b1000 A
b1000 G
1S
1]
1^
1f
1g
1o
1p
0x
0y
1I
1L
1O
0R
1[
1d
1m
0v
b111 5
b111 7
b111 C
b111 U
b1000 3
b1000 8
b1000 >
b1000 %
b1000 *
b1000 :
b1000 <
b0 &
b0 ,
b0 =
#25800
b1 &
b1 ,
b1 =
b1000 !"
#26000
b10 &
b10 ,
b10 =
#26200
b11 &
b11 ,
b11 =
#26400
b100 &
b100 ,
b100 =
#26600
b101 &
b101 ,
b101 =
#26800
b110 &
b110 ,
b110 =
#27000
b111 &
b111 ,
b111 =
#27200
b1000 &
b1000 ,
b1000 =
#27400
b1001 &
b1001 ,
b1001 =
#27600
b1010 &
b1010 ,
b1010 =
#27800
b1011 &
b1011 ,
b1011 =
#28000
b1100 &
b1100 ,
b1100 =
#28200
b1101 &
b1101 ,
b1101 =
#28400
b1110 &
b1110 ,
b1110 =
#28600
b1111 &
b1111 ,
b1111 =
#28800
0"
0S
1P
0D
b111 $
b111 4
b111 ?
1M
0E
b111 2
b111 A
b111 G
1J
0F
0]
0^
0I
0[
b110 5
b110 7
b110 C
b110 U
b1001 3
b1001 8
b1001 >
b1001 %
b1001 *
b1001 :
b1001 <
b0 &
b0 ,
b0 =
#29000
b1 &
b1 ,
b1 =
0}
b111 !"
#29200
b10 &
b10 ,
b10 =
#29400
b11 &
b11 ,
b11 =
#29600
b100 &
b100 ,
b100 =
#29800
b101 &
b101 ,
b101 =
#30000
b110 &
b110 ,
b110 =
#30200
b111 &
b111 ,
b111 =
#30400
b1000 &
b1000 ,
b1000 =
#30600
b1001 &
b1001 ,
b1001 =
#30800
b1010 &
b1010 ,
b1010 =
#31000
b1011 &
b1011 ,
b1011 =
#31200
b1100 &
b1100 ,
b1100 =
#31400
b1101 &
b1101 ,
b1101 =
#31600
b1110 &
b1110 ,
b1110 =
#31800
b1111 &
b1111 ,
b1111 =
#32000
b110 $
b110 4
b110 ?
0J
1F
b110 2
b110 A
b110 G
1M
1]
1^
0f
0g
1I
0L
1[
0d
b101 5
b101 7
b101 C
b101 U
b1010 3
b1010 8
b1010 >
b1010 %
b1010 *
b1010 :
b1010 <
b0 &
b0 ,
b0 =
#32200
b1 &
b1 ,
b1 =
b110 !"
#32400
b10 &
b10 ,
b10 =
#32600
b11 &
b11 ,
b11 =
#32800
b100 &
b100 ,
b100 =
#33000
b101 &
b101 ,
b101 =
#33200
b110 &
b110 ,
b110 =
#33400
b111 &
b111 ,
b111 =
#33600
b1000 &
b1000 ,
b1000 =
#33800
b1001 &
b1001 ,
b1001 =
#34000
b1010 &
b1010 ,
b1010 =
#34200
b1011 &
b1011 ,
b1011 =
#34400
b1100 &
b1100 ,
b1100 =
#34600
b1101 &
b1101 ,
b1101 =
#34800
b1110 &
b1110 ,
b1110 =
#35000
b1111 &
b1111 ,
b1111 =
#35200
b101 $
b101 4
b101 ?
0M
b101 2
b101 A
b101 G
1J
0F
0]
0^
0I
0[
b100 5
b100 7
b100 C
b100 U
b1011 3
b1011 8
b1011 >
b1011 %
b1011 *
b1011 :
b1011 <
b0 &
b0 ,
b0 =
#35400
b1 &
b1 ,
b1 =
b101 !"
#35600
b10 &
b10 ,
b10 =
#35800
b11 &
b11 ,
b11 =
#36000
b100 &
b100 ,
b100 =
#36200
b101 &
b101 ,
b101 =
#36400
b110 &
b110 ,
b110 =
#36600
b111 &
b111 ,
b111 =
#36800
b1000 &
b1000 ,
b1000 =
#37000
b1001 &
b1001 ,
b1001 =
#37200
b1010 &
b1010 ,
b1010 =
#37400
b1011 &
b1011 ,
b1011 =
#37600
b1100 &
b1100 ,
b1100 =
#37800
b1101 &
b1101 ,
b1101 =
#38000
b1110 &
b1110 ,
b1110 =
#38200
b1111 &
b1111 ,
b1111 =
#38400
1E
b100 $
b100 4
b100 ?
0J
1F
0M
b100 2
b100 A
b100 G
1P
1]
1^
1f
1g
0o
0p
1I
1L
0O
1[
1d
0m
b11 5
b11 7
b11 C
b11 U
b1100 3
b1100 8
b1100 >
b1100 %
b1100 *
b1100 :
b1100 <
b0 &
b0 ,
b0 =
#38600
b1 &
b1 ,
b1 =
b100 !"
#38800
b10 &
b10 ,
b10 =
#39000
b11 &
b11 ,
b11 =
#39200
b100 &
b100 ,
b100 =
#39400
b101 &
b101 ,
b101 =
#39600
b110 &
b110 ,
b110 =
#39800
b111 &
b111 ,
b111 =
#40000
b1000 &
b1000 ,
b1000 =
#40200
b1001 &
b1001 ,
b1001 =
#40400
b1010 &
b1010 ,
b1010 =
#40600
b1011 &
b1011 ,
b1011 =
#40800
b1100 &
b1100 ,
b1100 =
#41000
b1101 &
b1101 ,
b1101 =
#41200
b1110 &
b1110 ,
b1110 =
#41400
b1111 &
b1111 ,
b1111 =
#41600
0P
b11 $
b11 4
b11 ?
1M
0E
b11 2
b11 A
b11 G
1J
0F
0]
0^
0I
0[
b10 5
b10 7
b10 C
b10 U
b1101 3
b1101 8
b1101 >
b1101 %
b1101 *
b1101 :
b1101 <
b0 &
b0 ,
b0 =
#41800
b1 &
b1 ,
b1 =
b11 !"
#42000
b10 &
b10 ,
b10 =
#42200
b11 &
b11 ,
b11 =
#42400
b100 &
b100 ,
b100 =
#42600
b101 &
b101 ,
b101 =
#42800
b110 &
b110 ,
b110 =
#43000
b111 &
b111 ,
b111 =
#43200
b1000 &
b1000 ,
b1000 =
#43400
b1001 &
b1001 ,
b1001 =
#43600
b1010 &
b1010 ,
b1010 =
#43800
b1011 &
b1011 ,
b1011 =
#44000
b1100 &
b1100 ,
b1100 =
#44200
b1101 &
b1101 ,
b1101 =
#44400
b1110 &
b1110 ,
b1110 =
#44600
b1111 &
b1111 ,
b1111 =
#44800
0!
b10 $
b10 4
b10 ?
0J
1F
b10 2
b10 A
b10 G
1M
1]
1^
0f
0g
1I
0L
1[
0d
b1 5
b1 7
b1 C
b1 U
b1110 3
b1110 8
b1110 >
b1110 %
b1110 *
b1110 :
b1110 <
b0 &
b0 ,
b0 =
#45000
b1 &
b1 ,
b1 =
b10 !"
#45200
b10 &
b10 ,
b10 =
#45400
b11 &
b11 ,
b11 =
#45600
b100 &
b100 ,
b100 =
#45800
b101 &
b101 ,
b101 =
#46000
b110 &
b110 ,
b110 =
#46200
b111 &
b111 ,
b111 =
#46400
b1000 &
b1000 ,
b1000 =
#46600
b1001 &
b1001 ,
b1001 =
#46800
b1010 &
b1010 ,
b1010 =
#47000
b1011 &
b1011 ,
b1011 =
#47200
b1100 &
b1100 ,
b1100 =
#47400
b1101 &
b1101 ,
b1101 =
#47600
b1110 &
b1110 ,
b1110 =
#47800
b1111 &
b1111 ,
b1111 =
#48000
b1 $
b1 4
b1 ?
0M
b1 2
b1 A
b1 G
1J
0F
0]
0^
0I
0[
b0 5
b0 7
b0 C
b0 U
b1111 3
b1111 8
b1111 >
b1111 %
b1111 *
b1111 :
b1111 <
b0 &
b0 ,
b0 =
#48200
b1 &
b1 ,
b1 =
b1 !"
#48400
b10 &
b10 ,
b10 =
#48600
b11 &
b11 ,
b11 =
#48800
b100 &
b100 ,
b100 =
#49000
b101 &
b101 ,
b101 =
#49200
b110 &
b110 ,
b110 =
#49400
b111 &
b111 ,
b111 =
#49600
b1000 &
b1000 ,
b1000 =
#49800
b1001 &
b1001 ,
b1001 =
#50000
b1010 &
b1010 ,
b1010 =
#50200
b1011 &
b1011 ,
b1011 =
#50400
b1100 &
b1100 ,
b1100 =
#50600
b1101 &
b1101 ,
b1101 =
#50800
b1110 &
b1110 ,
b1110 =
#51000
b1111 &
b1111 ,
b1111 =
#51200
1!
1#
1D
0"
1E
b0 $
b0 4
b0 ?
1_
1h
1q
b1111 1
b1111 @
b1111 W
1z
0J
1F
0M
0P
b0 2
b0 A
b0 G
0S
1]
1^
1f
1g
1o
1p
1x
1y
1I
1L
1O
1R
1[
1d
1m
1v
b1111 5
b1111 7
b1111 C
b1111 U
10
b0 3
b0 8
b0 >
b1 '
b1 +
b1 V
b1 X
b1 `
b1 a
b1 i
b1 j
b1 r
b1 s
b1 {
b0 %
b0 *
b0 :
b0 <
b0 &
b0 ,
b0 =
#51400
0!
1"
1S
0#
1P
0D
b1111 $
b1111 4
b1111 ?
1M
0E
b1110 1
b1110 @
b1110 W
0_
b1111 2
b1111 A
b1111 G
1J
0F
0]
0^
0I
0[
b1110 5
b1110 7
b1110 C
b1110 U
b1 3
b1 8
b1 >
b1 &
b1 ,
b1 =
1~
1|
b10000 !"
#51600
b1110 $
b1110 4
b1110 ?
1_
b1101 1
b1101 @
b1101 W
0h
0J
1F
b1110 2
b1110 A
b1110 G
1M
1]
1^
0f
0g
1I
0L
1[
0d
b1101 5
b1101 7
b1101 C
b1101 U
b10 3
b10 8
b10 >
b10 &
b10 ,
b10 =
0~
1}
0|
b1111 !"
#51800
b1101 $
b1101 4
b1101 ?
0M
b1100 1
b1100 @
b1100 W
0_
b1101 2
b1101 A
b1101 G
1J
0F
0]
0^
0I
0[
b1100 5
b1100 7
b1100 C
b1100 U
b11 3
b11 8
b11 >
b11 &
b11 ,
b11 =
b1110 !"
#52000
1E
b1100 $
b1100 4
b1100 ?
1_
1h
b1011 1
b1011 @
b1011 W
0q
0J
1F
0M
b1100 2
b1100 A
b1100 G
1P
1]
1^
1f
1g
0o
0p
1I
1L
0O
1[
1d
0m
b1011 5
b1011 7
b1011 C
b1011 U
b100 3
b100 8
b100 >
b100 &
b100 ,
b100 =
b1101 !"
#52200
0P
b1011 $
b1011 4
b1011 ?
1M
0E
b1010 1
b1010 @
b1010 W
0_
b1011 2
b1011 A
b1011 G
1J
0F
0]
0^
0I
0[
b1010 5
b1010 7
b1010 C
b1010 U
b101 3
b101 8
b101 >
b101 &
b101 ,
b101 =
b1100 !"
