Practica_2/mux2_4.v
module mux2_4(output wire [3:0] Out, input wire [3:0] A, input wire [3:0] B, input wire s);
  
  assign Out = (s) ? A : B;
  
endmodule

Practica_2/mux4_1.v
module mux4_1(output reg out, input wire a, b, c, d, input wire [1:0] S);

  always @(a,b,c,d,S) begin
    case (S)
      2'b0: out = a;
      2'b1: out = b;
      2'b0: out = c;
      2'b1: out = d;
    endcase  
  end

endmodule

Practica_2/cl.v
module cl(output wire out, input wire a, input wire b, input wire [1:0] S);

  wire xor_out, not_out, and_out, or_out;  // SE DECLARAN LOS CABLES DE SALIDA DE LAS PUESTAS LÓGICAS
  xor xor_door (xor_out, a, b);  // SE DECLARA UNA PUERTA XOR A LA QUE LE ENTRA A Y B Y SALE EL CABLE XOR_OUT
  and and_door (and_out, a, b);  // SE DECLARA UNA PUERTA AND A LA QUE LE ENTRAN A Y B Y SALE AND_DOOR
  or or_door (or_out, a, b);  // SE DECLARA UNA PUERTA OR A LA QUE LE ENTRAN A Y B Y SALE OR_DOOR
  not not_door (not_out, a);  // SE DECLARA UNA PUERTA NOT A LA QUE LE ENTRAN A Y SALE NOT_DOOR
  mux4_1 mux_cl (out, xor_out, and_out, or_out, not_out, S);  // DECLARAMOS UN MUX4_1 AL QUE LE ENTRA COMO PARAMETROS LAS SALIDAS DE LAS PUERTAS LÓGICAS ANTERIORES, UNA SEÑAL DE SELECCIÓN S Y DA COMO SALIDA LA SEÑAL OUT DE LA CELDA LOGICA
                                                              
endmodule

Practica_2/ul4.v
module ul4(output wire[3:0] Out, input wire[3:0] A, input wire[3:0] B, input wire [1:0] S);

  cl cl_0(Out[0], A[0], B[0], S);
  cl cl_1(Out[1], A[1], B[1], S);
  cl cl_2(Out[2], A[2], B[2], S);
  cl cl_3(Out[3], A[3], B[3], S);

endmodule



// NO ENTIENDO COMO SE IMPLEMENTA LA UNIDAD LOGICA

Practica_2/fa.v
module fa(output wire c_out, sum, input wire a, b, c_in);
  
  fa fa1





endmodule

Practica_2/sum4.v
module sum4(output wire[3:0] S, output wire c_out, input wire[3:0] A, input wire[3:0] B, input wire c_in);
  
  wire carry1, carry2, carry3;
  
  fa fa_0(S[0], carry1, A[0], B[0], c_in);
  fa fa_1(S[1], carry2, A[1], B[1], carry1);
  fa fa_2(S[2], carry3, A[2], B[2], carry2);
  fa fa_3(S[3], c_out, A[3], B[3], carry3);

endmodule

Practica_2/compl1.v
module compl1(output wire [3:0] Out, input wire [3:0] Inp, input wire cpl);

  assign Out = cpl ? ~Inp : Inp;

endmodule

Practica_2/alu.v
module alu(output wire [3:0] R, output wire zero, carry, sign, input wire [3:0] A, B, input wire [1:0] ALUOp, input wire l);

  wire op1_A, op2_B, cpl, cin0;
  wire [3:0] OP1, OP2, mux2_out, sum4_out, ul4_out;

  mux2_4 mux2_4_1 (OP1, 4'b0000, A, op1_A);
  mux2_4 mux2_4_2 (mux2_out, A, B, op2_B);
  compl1 compl1_1 (OP2, mux2_out, cpl);
  sum4 sum4_1 (sum4_out, carry, OP1, OP2, cin0);
  ul4 ul4_1 (ul4_out, OP1, OP2, ALUOp);
  mux2_4 mux2_4_3 (R, sum4_out, ul4_out, l);

  assign zero = ~(R[0]|R[1]|R[2]|R[3]);
  assign sign = R[3];

  assign op1_A = l | ALUOp[1];
  assign op2_B = l | ALUOp[1] | ALUOp[0];
  assign cpl = ((~l) & (~ALUOp[1])) | ((~l) & ALUOp[0]);
  assign cin0 = (~ALUOp[1]) | ALUOp[0];

endmodule

// EJECUCION
// $ iverilog -o ripple ripple_carry_adder.v ripple_carry_adder_tb.v
// $ vvp ripple

Practica_2/alu_tb.v
// Testbench para modulo alu
`timescale 1 ns / 10 ps //Directiva que fija la unidad de tiempo de simulación y la precision de la unidad
module alu_tb;
//declaracion de señales
reg [1:0] t_Op;
reg t_l;
reg [3:0] t_A, t_B;
wire [3:0] t_R;
wire t_z, t_c, t_s;
integer errores;
//instancia del modulo a testear
alu mat(t_R, t_z, t_c, t_s, t_A, t_B, t_Op, t_l);
initial
begin
  $dumpfile("alu.vcd");
  $dumpvars;
  $monitor("tiempo=%0d A=%b B=%b L=%b Op=%b R=%b, Z=%b, C=%b, S=%b", $time, t_A, t_B, t_l, t_Op, t_R, t_z, t_c, t_s);

  errores = 0;
  t_l = 1'b0;
  repeat(2)
	begin
	t_Op = 2'b0;
	repeat(4)
		begin
		  t_A = 4'b0;
		  repeat(16) 
		  begin
			t_B = 4'b0;
			repeat(16) 
			begin
				# 2 check;
				t_B = t_B + 1;
			end
			t_A = t_A + 1;
		  end
		  t_Op = t_Op + 1;
		end
		t_l = t_l + 1;
	end
	$display("Encontradas %d operaciones erroneas", errores);
  //fin simulacion
  $finish;
end

// Tarea para hacer la comprobación automática de resultados
task check;
reg [4:0] result;
reg flag_zero, flag_carry, flag_sign;
begin
	// Si las operaciones son lógicas
	if (t_l)
	begin
		case (t_Op)
			2'b00: result[3:0] = t_A & t_B;
			2'b01: result[3:0] = t_A | t_B;
			2'b10: result[3:0] = t_A ^ t_B;
			2'b11: result[3:0] = ~t_A;
			default: $display("ERROR. Valor no esperado para t_Op: %b", t_Op);
		endcase
		flag_carry = 1'bx;
		flag_sign = 1'bx;
	end
	else
	begin
		case (t_Op)
			2'b00: result = (t_A ^4'b1111) + 4'b0001;
			2'b01: result = (t_B ^4'b1111) + 4'b0001;
			2'b10: result = t_A + t_B;
			2'b11: result = t_A + ((t_B ^4'b1111) + 1);
			default: $display("ERROR. Valor no esperado para t_Op: %b", t_Op);
		endcase
		flag_carry = result[4];
		flag_sign = result[3];
		if (flag_sign !== t_s || flag_carry !== t_c)
		begin
			errores = errores + 1;
			$display("ERROR con operacion L=%b, OP=%b A=%b B=%b", t_l, t_Op, t_A, t_B);
			if (flag_sign !== t_s)
				$display("ERROR. Flag de signo esperado %b, obtenido %b", flag_sign, t_s);
			if (flag_carry !== t_c)
				$display("\tFlag de acarreo esperado %b, obtenido %b", flag_carry, t_c);
		end
	end

	flag_zero = ~| result[3:0];
	if (result[3:0] !== t_R || flag_zero !== t_z)
	begin
		errores = errores + 1;
		$display("ERROR con operacion L=%b, OP=%b A=%b B=%b", t_l, t_Op, t_A, t_B);
		if (result[3:0] !== t_R)
			$display("\tResultado esperado %b, obtenido %b", result[3:0], t_R);
		if (flag_zero !== t_z)
			$display("\tFlag de cero esperado %b, obtenido %b", flag_zero, t_z);
	end
end
endtask
endmodule

Practica_2/alu.vcd
$date
	Tue Nov  8 15:19:45 2022
$end
$version
	Icarus Verilog
$end
$timescale
	10ps
$end
$scope module alu_tb $end
$var wire 1 ! t_z $end
$var wire 1 " t_s $end
$var wire 1 # t_c $end
$var wire 4 $ t_R [3:0] $end
$var reg 4 % t_A [3:0] $end
$var reg 4 & t_B [3:0] $end
$var reg 2 ' t_Op [1:0] $end
$var reg 1 ( t_l $end
$var integer 32 ) errores [31:0] $end
$scope module mat $end
$var wire 4 * A [3:0] $end
$var wire 2 + ALUOp [1:0] $end
$var wire 4 , B [3:0] $end
$var wire 1 - cin0 $end
$var wire 1 . cpl $end
$var wire 1 ( l $end
$var wire 1 / op1_A $end
$var wire 1 0 op2_B $end
$var wire 1 ! zero $end
$var wire 4 1 ul4_out [3:0] $end
$var wire 4 2 sum4_out [3:0] $end
$var wire 1 " sign $end
$var wire 4 3 mux2_out [3:0] $end
$var wire 1 # carry $end
$var wire 4 4 R [3:0] $end
$var wire 4 5 OP2 [3:0] $end
$var wire 4 6 OP1 [3:0] $end
$scope module compl1_1 $end
$var wire 1 . cpl $end
$var wire 4 7 Out [3:0] $end
$var wire 4 8 Inp [3:0] $end
$upscope $end
$scope module mux2_4_1 $end
$var wire 4 9 A [3:0] $end
$var wire 4 : B [3:0] $end
$var wire 1 / s $end
$var wire 4 ; Out [3:0] $end
$upscope $end
$scope module mux2_4_2 $end
$var wire 4 < A [3:0] $end
$var wire 4 = B [3:0] $end
$var wire 1 0 s $end
$var wire 4 > Out [3:0] $end
$upscope $end
$scope module mux2_4_3 $end
$var wire 1 ( s $end
$var wire 4 ? Out [3:0] $end
$var wire 4 @ B [3:0] $end
$var wire 4 A A [3:0] $end
$upscope $end
$scope module sum4_1 $end
$var wire 4 B A [3:0] $end
$var wire 4 C B [3:0] $end
$var wire 1 - c_in $end
$var wire 1 D carry3 $end
$var wire 1 E carry2 $end
$var wire 1 F carry1 $end
$var wire 1 # c_out $end
$var wire 4 G S [3:0] $end
$scope module fa_0 $end
$var wire 1 H a $end
$var wire 1 I b $end
$var wire 1 - c_in $end
$var wire 1 F sum $end
$var wire 1 J c_out $end
$upscope $end
$scope module fa_1 $end
$var wire 1 K a $end
$var wire 1 L b $end
$var wire 1 F c_in $end
$var wire 1 E sum $end
$var wire 1 M c_out $end
$upscope $end
$scope module fa_2 $end
$var wire 1 N a $end
$var wire 1 O b $end
$var wire 1 E c_in $end
$var wire 1 D sum $end
$var wire 1 P c_out $end
$upscope $end
$scope module fa_3 $end
$var wire 1 Q a $end
$var wire 1 R b $end
$var wire 1 D c_in $end
$var wire 1 # sum $end
$var wire 1 S c_out $end
$upscope $end
$upscope $end
$scope module ul4_1 $end
$var wire 4 T A [3:0] $end
$var wire 4 U B [3:0] $end
$var wire 2 V S [1:0] $end
$var wire 4 W Out [3:0] $end
$scope module cl_0 $end
$var wire 2 X S [1:0] $end
$var wire 1 Y a $end
$var wire 1 Z and_out $end
$var wire 1 [ b $end
$var wire 1 \ not_out $end
$var wire 1 ] or_out $end
$var wire 1 ^ xor_out $end
$var wire 1 _ out $end
$scope module mux_cl $end
$var wire 2 ` S [1:0] $end
$var wire 1 ^ a $end
$var wire 1 Z b $end
$var wire 1 ] c $end
$var wire 1 \ d $end
$var reg 1 _ out $end
$upscope $end
$upscope $end
$scope module cl_1 $end
$var wire 2 a S [1:0] $end
$var wire 1 b a $end
$var wire 1 c and_out $end
$var wire 1 d b $end
$var wire 1 e not_out $end
$var wire 1 f or_out $end
$var wire 1 g xor_out $end
$var wire 1 h out $end
$scope module mux_cl $end
$var wire 2 i S [1:0] $end
$var wire 1 g a $end
$var wire 1 c b $end
$var wire 1 f c $end
$var wire 1 e d $end
$var reg 1 h out $end
$upscope $end
$upscope $end
$scope module cl_2 $end
$var wire 2 j S [1:0] $end
$var wire 1 k a $end
$var wire 1 l and_out $end
$var wire 1 m b $end
$var wire 1 n not_out $end
$var wire 1 o or_out $end
$var wire 1 p xor_out $end
$var wire 1 q out $end
$scope module mux_cl $end
$var wire 2 r S [1:0] $end
$var wire 1 p a $end
$var wire 1 l b $end
$var wire 1 o c $end
$var wire 1 n d $end
$var reg 1 q out $end
$upscope $end
$upscope $end
$scope module cl_3 $end
$var wire 2 s S [1:0] $end
$var wire 1 t a $end
$var wire 1 u and_out $end
$var wire 1 v b $end
$var wire 1 w not_out $end
$var wire 1 x or_out $end
$var wire 1 y xor_out $end
$var wire 1 z out $end
$scope module mux_cl $end
$var wire 2 { S [1:0] $end
$var wire 1 y a $end
$var wire 1 u b $end
$var wire 1 x c $end
$var wire 1 w d $end
$var reg 1 z out $end
$upscope $end
$upscope $end
$upscope $end
$upscope $end
$scope task check $end
$var reg 1 | flag_carry $end
$var reg 1 } flag_sign $end
$var reg 1 ~ flag_zero $end
$var reg 5 !" result [4:0] $end
$upscope $end
$upscope $end
$enddefinitions $end
#0
$dumpvars
bx !"
x~
x}
x|
b0 {
1z
1y
1x
1w
1v
0u
0t
b0 s
b0 r
1q
1p
1o
1n
1m
0l
0k
b0 j
b0 i
1h
1g
1f
1e
1d
0c
0b
b0 a
b0 `
1_
1^
1]
1\
1[
0Z
0Y
b0 X
b1111 W
b0 V
b1111 U
b0 T
0S
1R
0Q
1P
1O
0N
0M
1L
0K
1J
1I
0H
b101 G
0F
1E
0D
b1111 C
b0 B
b101 A
b1111 @
b1111 ?
b0 >
b0 =
b0 <
b0 ;
b0 :
b0 9
b0 8
b1111 7
b0 6
b1111 5
b1111 4
b0 3
b101 2
b1111 1
00
0/
1.
1-
b0 ,
b0 +
b0 *
b0 )
0(
b0 '
b0 &
b0 %
b1111 $
1#
1"
0!
$end
#200
0#
1S
1D
0P
b1110 $
b1110 4
b1110 ?
0E
1M
b1110 1
b1110 @
b1110 W
0_
1F
b1010 2
b1010 A
b1010 G
0J
0]
0^
0I
0[
b1110 5
b1110 7
b1110 C
b1110 U
b1 3
b1 8
b1 >
b1 &
b1 ,
b1 =
1~
b10 )
0}
1|
b10000 !"
#400
0#
1S
b1101 $
b1101 4
b1101 ?
1D
0P
1_
b1101 1
b1101 @
b1101 W
0h
0F
1J
0E
b1001 2
b1001 A
b1001 G
0M
1]
1^
0f
0g
1I
0L
1[
0d
b1101 5
b1101 7
b1101 C
b1101 U
b10 3
b10 8
b10 >
b10 &
b10 ,
b10 =
b100 )
#600
1#
0S
0D
1P
b1100 $
b1100 4
b1100 ?
1E
b1100 1
b1100 @
b1100 W
0_
1F
b100 2
b100 A
b100 G
0J
0]
0^
0I
0[
b1100 5
b1100 7
b1100 C
b1100 U
b11 3
b11 8
b11 >
b11 &
b11 ,
b11 =
b110 )
#800
b1011 $
b1011 4
b1011 ?
0#
1S
1_
1h
b1011 1
b1011 @
b1011 W
0q
0F
1J
1E
0M
1D
b1001 2
b1001 A
b1001 G
0P
1]
1^
1f
1g
0o
0p
1I
1L
0O
1[
1d
0m
b1011 5
b1011 7
b1011 C
b1011 U
b100 3
b100 8
b100 >
b100 &
b100 ,
b100 =
b1000 )
#1000
1#
0S
0D
b1010 $
b1010 4
b1010 ?
0E
1M
b1010 1
b1010 @
b1010 W
0_
1F
b10 2
b10 A
b10 G
0J
0]
0^
0I
0[
b1010 5
b1010 7
b1010 C
b1010 U
b101 3
b101 8
b101 >
b101 &
b101 ,
b101 =
b1010 )
#1200
1#
0S
b1001 $
b1001 4
b1001 ?
0D
1_
b1001 1
b1001 @
b1001 W
0h
0F
1J
0E
b1 2
b1 A
b1 G
0M
1]
1^
0f
0g
1I
0L
1[
0d
b1001 5
b1001 7
b1001 C
b1001 U
b110 3
b110 8
b110 >
b110 &
b110 ,
b110 =
b1100 )
#1400
0#
1S
1D
b1000 $
b1000 4
b1000 ?
1E
b1000 1
b1000 @
b1000 W
0_
1F
b1000 2
b1000 A
b1000 G
0J
0]
0^
0I
0[
b1000 5
b1000 7
b1000 C
b1000 U
b111 3
b111 8
b111 >
b111 &
b111 ,
b111 =
b1110 )
#1600
0"
b111 $
b111 4
b111 ?
1_
1h
1q
b111 1
b111 @
b111 W
0z
0F
1J
1E
0M
0D
1P
0#
b101 2
b101 A
b101 G
0S
1]
1^
1f
1g
1o
1p
0x
0y
1I
1L
1O
0R
1[
1d
1m
0v
b111 5
b111 7
b111 C
b111 U
b1000 3
b1000 8
b1000 >
b1000 &
b1000 ,
b1000 =
b10000 )
#1800
1#
1D
0P
b110 $
b110 4
b110 ?
0E
1M
b110 1
b110 @
b110 W
0_
1F
b10 2
b10 A
b10 G
0J
0]
0^
0I
0[
b110 5
b110 7
b110 C
b110 U
b1001 3
b1001 8
b1001 >
b1001 &
b1001 ,
b1001 =
b10010 )
#2000
1#
b101 $
b101 4
b101 ?
1D
0P
1_
b101 1
b101 @
b101 W
0h
0F
1J
0E
b1 2
b1 A
b1 G
0M
1]
1^
0f
0g
1I
0L
1[
0d
b101 5
b101 7
b101 C
b101 U
b1010 3
b1010 8
b1010 >
b1010 &
b1010 ,
b1010 =
b10011 )
#2200
0#
0D
1P
b100 $
b100 4
b100 ?
1E
b100 1
b100 @
b100 W
0_
1F
b100 2
b100 A
b100 G
0J
0]
0^
0I
0[
b100 5
b100 7
b100 C
b100 U
b1011 3
b1011 8
b1011 >
b1011 &
b1011 ,
b1011 =
b10100 )
#2400
b11 $
b11 4
b11 ?
1#
1_
1h
b11 1
b11 @
b11 W
0q
0F
1J
1E
0M
1D
b1 2
b1 A
b1 G
0P
1]
1^
1f
1g
0o
0p
1I
1L
0O
1[
1d
0m
b11 5
b11 7
b11 C
b11 U
b1100 3
b1100 8
b1100 >
b1100 &
b1100 ,
b1100 =
b10110 )
#2600
0#
0D
b10 $
b10 4
b10 ?
0E
1M
b10 1
b10 @
b10 W
0_
1F
b10 2
b10 A
b10 G
0J
0]
0^
0I
0[
b10 5
b10 7
b10 C
b10 U
b1101 3
b1101 8
b1101 >
b1101 &
b1101 ,
b1101 =
b10111 )
#2800
0#
b1 $
b1 4
b1 ?
0D
1_
b1 1
b1 @
b1 W
0h
0F
1J
0E
b1 2
b1 A
b1 G
0M
1]
1^
0f
0g
1I
0L
1[
0d
b1 5
b1 7
b1 C
b1 U
b1110 3
b1110 8
b1110 >
b1110 &
b1110 ,
b1110 =
b11001 )
#3000
1!
1#
1D
b0 $
b0 4
b0 ?
1E
b0 1
b0 @
b0 W
0_
1F
b0 2
b0 A
b0 G
0J
0]
0^
0I
0[
b0 5
b0 7
b0 C
b0 U
b1111 3
b1111 8
b1111 >
b1111 &
b1111 ,
b1111 =
b11011 )
#3200
0!
1"
0E
1M
1h
1q
1z
b1110 $
b1110 4
b1110 ?
1D
0P
0#
1S
1Z
1f
1g
1o
1p
1x
1y
b1110 1
b1110 @
b1110 W
0_
1I
1L
1O
1R
1[
1d
1m
1v
1F
b1011 2
b1011 A
b1011 G
1J
1]
0^
0\
b1111 5
b1111 7
b1111 C
b1111 U
1H
1Y
b1 6
b1 ;
b1 B
b1 T
b0 3
b0 8
b0 >
b1 %
b1 *
b1 :
b1 <
b0 &
b0 ,
b0 =
#3400
1#
0S
0D
1P
b1111 $
b1111 4
b1111 ?
1E
b101 2
b101 A
b101 G
0M
b1111 1
b1111 @
b1111 W
1_
0F
0Z
1^
0I
0[
b1110 5
b1110 7
b1110 C
b1110 U
b1 3
b1 8
b1 >
b1 &
b1 ,
b1 =
b11100 )
0~
1}
0|
b1111 !"
#3600
1#
0S
b1100 $
b1100 4
b1100 ?
0D
b101 2
b101 A
b101 G
1P
0_
b1100 1
b1100 @
b1100 W
0h
1F
1E
1Z
0^
0f
0g
1I
0L
1[
0d
b1101 5
b1101 7
b1101 C
b1101 U
b10 3
b10 8
b10 >
b10 &
b10 ,
b10 =
b11101 )
#3800
0#
1S
1D
b1001 2
b1001 A
b1001 G
0P
b1101 $
b1101 4
b1101 ?
0E
b1101 1
b1101 @
b1101 W
1_
0F
0Z
1^
0I
0[
b1100 5
b1100 7
b1100 C
b1100 U
b11 3
b11 8
b11 >
b11 &
b11 ,
b11 =
b11111 )
#4000
b1010 $
b1010 4
b1010 ?
1M
1#
b11 2
b11 A
b11 G
0S
0_
1h
b1010 1
b1010 @
b1010 W
0q
1F
0E
0D
1Z
0^
1f
1g
0o
0p
1I
1L
0O
1[
1d
0m
b1011 5
b1011 7
b1011 C
b1011 U
b100 3
b100 8
b100 >
b100 &
b100 ,
b100 =
b100000 )
#4200
0#
1S
1D
b1011 $
b1011 4
b1011 ?
1E
b1001 2
b1001 A
b1001 G
0M
b1011 1
b1011 @
b1011 W
1_
0F
0Z
1^
0I
0[
b1010 5
b1010 7
b1010 C
b1010 U
b101 3
b101 8
b101 >
b101 &
b101 ,
b101 =
b100010 )
#4400
0#
b1001 2
b1001 A
b1001 G
1S
b1000 $
b1000 4
b1000 ?
1D
0_
b1000 1
b1000 @
b1000 W
0h
1F
1E
1Z
0^
0f
0g
1I
0L
1[
0d
b1001 5
b1001 7
b1001 C
b1001 U
b110 3
b110 8
b110 >
b110 &
b110 ,
b110 =
b100011 )
#4600
1#
b1 2
b1 A
b1 G
0S
0D
b1001 $
b1001 4
b1001 ?
0E
b1001 1
b1001 @
b1001 W
1_
0F
0Z
1^
0I
0[
b1000 5
b1000 7
b1000 C
b1000 U
b111 3
b111 8
b111 >
b111 &
b111 ,
b111 =
b100100 )
#4800
0"
b110 $
b110 4
b110 ?
1M
b11 2
b11 A
b11 G
0P
0_
1h
1q
b110 1
b110 @
b110 W
0z
1F
0E
1D
1#
1Z
0^
1f
1g
1o
1p
0x
0y
1I
1L
1O
0R
1[
1d
1m
0v
b111 5
b111 7
b111 C
b111 U
b1000 3
b1000 8
b1000 >
b1000 &
b1000 ,
b1000 =
b100110 )
#5000
0#
0D
1P
b111 $
b111 4
b111 ?
1E
b101 2
b101 A
b101 G
0M
b111 1
b111 @
b111 W
1_
0F
0Z
1^
0I
0[
b110 5
b110 7
b110 C
b110 U
b1001 3
b1001 8
b1001 >
b1001 &
b1001 ,
b1001 =
b101000 )
#5200
0#
b100 $
b100 4
b100 ?
0D
b101 2
b101 A
b101 G
1P
0_
b100 1
b100 @
b100 W
0h
1F
1E
1Z
0^
0f
0g
1I
0L
1[
0d
b101 5
b101 7
b101 C
b101 U
b1010 3
b1010 8
b1010 >
b1010 &
b1010 ,
b1010 =
b101010 )
#5400
1#
1D
b1 2
b1 A
b1 G
0P
b101 $
b101 4
b101 ?
0E
b101 1
b101 @
b101 W
1_
0F
0Z
1^
0I
0[
b100 5
b100 7
b100 C
b100 U
b1011 3
b1011 8
b1011 >
b1011 &
b1011 ,
b1011 =
b101100 )
#5600
b10 $
b10 4
b10 ?
b11 2
b11 A
b11 G
1M
0#
0_
1h
b10 1
b10 @
b10 W
0q
1F
0E
0D
1Z
0^
1f
1g
0o
0p
1I
1L
0O
1[
1d
0m
b11 5
b11 7
b11 C
b11 U
b1100 3
b1100 8
b1100 >
b1100 &
b1100 ,
b1100 =
b101110 )
#5800
1#
1D
b11 $
b11 4
b11 ?
1E
b1 2
b1 A
b1 G
0M
b11 1
b11 @
b11 W
1_
0F
0Z
1^
0I
0[
b10 5
b10 7
b10 C
b10 U
b1101 3
b1101 8
b1101 >
b1101 &
b1101 ,
b1101 =
b110000 )
#6000
1!
1#
b0 $
b0 4
b0 ?
1D
0_
b0 1
b0 @
b0 W
0h
1F
1E
1Z
0^
0f
0g
1I
0L
1[
0d
b1 5
b1 7
b1 C
b1 U
b1110 3
b1110 8
b1110 >
b1110 &
b1110 ,
b1110 =
b110010 )
#6200
0!
0#
0D
b1 $
b1 4
b1 ?
0E
b1 1
b1 @
b1 W
1_
0F
0Z
1^
0I
0[
b0 5
b0 7
b0 C
b0 U
b1111 3
b1111 8
b1111 >
b1111 &
b1111 ,
b1111 =
b110100 )
#6400
1S
1"
1D
1q
1z
b1101 $
b1101 4
b1101 ?
0P
0#
1c
1o
1p
1x
1y
1M
1_
b1101 1
b1101 @
b1101 W
0h
1I
1L
1O
1R
1[
1d
1m
1v
0F
b1011 2
b1011 A
b1011 G
1J
0E
1]
1^
1\
1f
0g
0e
b1111 5
b1111 7
b1111 C
b1111 U
0H
1K
0Y
1b
b10 6
b10 ;
b10 B
b10 T
b0 3
b0 8
b0 >
b10 %
b10 *
b10 :
b10 <
b0 &
b0 ,
b0 =
b110110 )
#6600
1#
0S
0D
1P
b1100 $
b1100 4
b1100 ?
1E
b1100 1
b1100 @
b1100 W
0_
1F
b110 2
b110 A
b110 G
0J
0]
0^
0I
0[
b1110 5
b1110 7
b1110 C
b1110 U
b1 3
b1 8
b1 >
b1 &
b1 ,
b1 =
b110111 )
b1110 !"
#6800
1#
0S
b1111 $
b1111 4
b1111 ?
0M
0D
1P
1_
b1111 1
b1111 @
b1111 W
1h
0F
b101 2
b101 A
b101 G
1J
1E
1]
1^
0c
1g
1I
0L
1[
0d
b1101 5
b1101 7
b1101 C
b1101 U
b10 3
b10 8
b10 >
b10 &
b10 ,
b10 =
b111001 )
#7000
0#
1S
1D
0P
b1110 $
b1110 4
b1110 ?
0E
1M
b1110 1
b1110 @
b1110 W
0_
1F
b1010 2
b1010 A
b1010 G
0J
0]
0^
0I
0[
b1100 5
b1100 7
b1100 C
b1100 U
b11 3
b11 8
b11 >
b11 &
b11 ,
b11 =
b111011 )
#7200
b1001 $
b1001 4
b1001 ?
1#
0S
1_
0h
b1001 1
b1001 @
b1001 W
0q
0F
b11 2
b11 A
b11 G
1J
0E
0D
1]
1^
1c
0g
0o
0p
1I
1L
0O
1[
1d
0m
b1011 5
b1011 7
b1011 C
b1011 U
b100 3
b100 8
b100 >
b100 &
b100 ,
b100 =
#7400
0#
1S
1D
b1000 $
b1000 4
b1000 ?
1E
b1000 1
b1000 @
b1000 W
0_
1F
b1010 2
b1010 A
b1010 G
0J
0]
0^
0I
0[
b1010 5
b1010 7
b1010 C
b1010 U
b101 3
b101 8
b101 >
b101 &
b101 ,
b101 =
b111101 )
#7600
0#
1S
b1011 $
b1011 4
b1011 ?
0M
1D
1_
b1011 1
b1011 @
b1011 W
1h
0F
b1001 2
b1001 A
b1001 G
1J
1E
1]
1^
0c
1g
1I
0L
1[
0d
b1001 5
b1001 7
b1001 C
b1001 U
b110 3
b110 8
b110 >
b110 &
b110 ,
b110 =
b111110 )
#7800
1#
0S
0D
b1010 $
b1010 4
b1010 ?
0E
1M
b1010 1
b1010 @
b1010 W
0_
1F
b10 2
b10 A
b10 G
0J
0]
0^
0I
0[
b1000 5
b1000 7
b1000 C
b1000 U
b111 3
b111 8
b111 >
b111 &
b111 ,
b111 =
b111111 )
#8000
0"
b101 $
b101 4
b101 ?
0P
1_
0h
1q
b101 1
b101 @
b101 W
0z
0F
b11 2
b11 A
b11 G
1J
0E
1D
1#
1]
1^
1c
0g
1o
1p
0x
0y
1I
1L
1O
0R
1[
1d
1m
0v
b111 5
b111 7
b111 C
b111 U
b1000 3
b1000 8
b1000 >
b1000 &
b1000 ,
b1000 =
b1000001 )
#8200
0#
0D
1P
b100 $
b100 4
b100 ?
1E
b100 1
b100 @
b100 W
0_
1F
b110 2
b110 A
b110 G
0J
0]
0^
0I
0[
b110 5
b110 7
b110 C
b110 U
b1001 3
b1001 8
b1001 >
b1001 &
b1001 ,
b1001 =
b1000011 )
#8400
0#
b111 $
b111 4
b111 ?
0M
0D
1P
1_
b111 1
b111 @
b111 W
1h
0F
b101 2
b101 A
b101 G
1J
1E
1]
1^
0c
1g
1I
0L
1[
0d
b101 5
b101 7
b101 C
b101 U
b1010 3
b1010 8
b1010 >
b1010 &
b1010 ,
b1010 =
b1000101 )
#8600
1#
1D
0P
b110 $
b110 4
b110 ?
0E
1M
b110 1
b110 @
b110 W
0_
1F
b10 2
b10 A
b10 G
0J
0]
0^
0I
0[
b100 5
b100 7
b100 C
b100 U
b1011 3
b1011 8
b1011 >
b1011 &
b1011 ,
b1011 =
b1000111 )
#8800
b1 $
b1 4
b1 ?
0#
1_
0h
b1 1
b1 @
b1 W
0q
0F
b11 2
b11 A
b11 G
1J
0E
0D
1]
1^
1c
0g
0o
0p
1I
1L
0O
1[
1d
0m
b11 5
b11 7
b11 C
b11 U
b1100 3
b1100 8
b1100 >
b1100 &
b1100 ,
b1100 =
b1001001 )
#9000
1!
1#
1D
b0 $
b0 4
b0 ?
1E
b0 1
b0 @
b0 W
0_
1F
b10 2
b10 A
b10 G
0J
0]
0^
0I
0[
b10 5
b10 7
b10 C
b10 U
b1101 3
b1101 8
b1101 >
b1101 &
b1101 ,
b1101 =
b1001011 )
#9200
0!
1#
b11 $
b11 4
b11 ?
0M
1D
1_
b11 1
b11 @
b11 W
1h
0F
b1 2
b1 A
b1 G
1J
1E
1]
1^
0c
1g
1I
0L
1[
0d
b1 5
b1 7
b1 C
b1 U
b1110 3
b1110 8
b1110 >
b1110 &
b1110 ,
b1110 =
b1001101 )
#9400
0#
0D
b10 $
b10 4
b10 ?
0E
1M
b10 1
b10 @
b10 W
0_
1F
b10 2
b10 A
b10 G
0J
0]
0^
0I
0[
b0 5
b0 7
b0 C
b0 U
b1111 3
b1111 8
b1111 >
b1111 &
b1111 ,
b1111 =
b1001111 )
#9600
1"
1P
1E
0S
0h
1q
1z
b1100 $
b1100 4
b1100 ?
0D
1#
1Z
1c
0g
1o
1p
1x
1y
b1100 1
b1100 @
b1100 W
0_
1I
1L
1O
1R
1[
1d
1m
1v
1F
b111 2
b111 A
b111 G
1J
1]
0^
0\
b1111 5
b1111 7
b1111 C
b1111 U
1H
1Y
b11 6
b11 ;
b11 B
b11 T
b0 3
b0 8
b0 >
b11 %
b11 *
b11 :
b11 <
b0 &
b0 ,
b0 =
b1010001 )
#9800
0#
1S
1D
b1011 2
b1011 A
b1011 G
0P
b1101 $
b1101 4
b1101 ?
0E
b1101 1
b1101 @
b1101 W
1_
0F
0Z
1^
0I
0[
b1110 5
b1110 7
b1110 C
b1110 U
b1 3
b1 8
b1 >
b1 &
b1 ,
b1 =
b1010011 )
b1101 !"
#10000
0#
1S
b1110 $
b1110 4
b1110 ?
1D
0P
0_
b1110 1
b1110 @
b1110 W
1h
1F
0E
b1011 2
b1011 A
b1011 G
1M
1Z
0^
0c
1g
1I
0L
1[
0d
b1101 5
b1101 7
b1101 C
b1101 U
b10 3
b10 8
b10 >
b10 &
b10 ,
b10 =
#10200
1#
0S
0D
1P
b1111 $
b1111 4
b1111 ?
1E
b101 2
b101 A
b101 G
0M
b1111 1
b1111 @
b1111 W
1_
0F
0Z
1^
0I
0[
b1100 5
b1100 7
b1100 C
b1100 U
b11 3
b11 8
b11 >
b11 &
b11 ,
b11 =
b1010100 )
#10400
b1000 $
b1000 4
b1000 ?
0#
1S
0_
0h
b1000 1
b1000 @
b1000 W
0q
1F
1E
1M
1D
b1011 2
b1011 A
b1011 G
0P
1Z
0^
1c
0g
0o
0p
1I
1L
0O
1[
1d
0m
b1011 5
b1011 7
b1011 C
b1011 U
b100 3
b100 8
b100 >
b100 &
b100 ,
b100 =
b1010110 )
#10600
1#
b11 2
b11 A
b11 G
0S
0D
b1001 $
b1001 4
b1001 ?
0E
b1001 1
b1001 @
b1001 W
1_
0F
0Z
1^
0I
0[
b1010 5
b1010 7
b1010 C
b1010 U
b101 3
b101 8
b101 >
b101 &
b101 ,
b101 =
b1010111 )
